fsAbstractPlatformMonitor.py
fsDirectory.py
fsDropBox.py
fsDropBoxMonitorClient.py
fsFileServer.py
fsLists.py
fsMac-10-5-Monitor.py
fsMonitor.py
fsMonitorServer.py
fsNotificationScheduler.py
fsPyinotifyMonitor.py
fsServerFS.py
fsServerMS.py
fsUtil.py
fsWin-XP-Monitor.py
omero_dropbox-5.7.0.dist-info/LICENSE.txt
omero_dropbox-5.7.0.dist-info/METADATA
omero_dropbox-5.7.0.dist-info/WHEEL
omero_dropbox-5.7.0.dist-info/top_level.txt
omero_dropbox-5.7.0.dist-info/RECORD
