Metadata-Version: 2.1
Name: omero-dropbox
Version: 5.7.0
Summary: OMERO.dropbox server for watching directories
Home-page: https://docs.openmicroscopy.org/latest/omero/developers/Server/FS.html
Author: The Open Microscopy Team
Author-email: ome-devel@lists.openmicroscopy.org.uk
Classifier: Development Status :: 5 - Production/Stable
Classifier: Intended Audience :: Developers
Classifier: Intended Audience :: Science/Research
Classifier: Intended Audience :: System Administrators
Classifier: License :: OSI Approved :: GNU General Public License v2 or later (GPLv2+)
Classifier: Natural Language :: English
Classifier: Operating System :: OS Independent
Classifier: Programming Language :: Python :: 3
Classifier: Topic :: Software Development :: Libraries :: Python Modules
Requires-Python: >=3.8
License-File: LICENSE.txt
Requires-Dist: omero-py
